Megabank_PS_Packaging/PS_Packaging.py
Megabank_PS_Packaging/__init__.py
Megabank_PS-0.1.dist-info/License.txt
Megabank_PS-0.1.dist-info/METADATA
Megabank_PS-0.1.dist-info/WHEEL
Megabank_PS-0.1.dist-info/top_level.txt
Megabank_PS-0.1.dist-info/RECORD
