Metadata-Version: 2.1
Name: Megabank-PS
Version: 0.1
Summary: Package that provides common functions which are used in a bank
Author: Parth
Author-email: mohrilparth@gmail.com
License: MIT
License-File: License.txt
Requires-Dist: pandas
